{
  "7351a786": "calcAllTokensInGivenExactBptOut(uint256[],uint256,uint256)",
  "76a38e91": "calcInGivenOut(uint256,uint256,uint256,uint256)",
  "2ae568a9": "calcNewtonDelta(uint256,uint256,uint256,uint256,uint256,uint256)",
  "72ee6341": "calcOutGivenIn(uint256,uint256,uint256,uint256)",
  "c3211cd0": "calcProtocolFees(uint256,uint256,uint256,uint256,uint256)",
  "f442dbc4": "calcTokensOutGivenExactBptIn(uint256[],uint256,uint256)",
  "9457b3cf": "calculateCubic(uint256,uint256,uint256,uint256,uint256)",
  "38c9bfc4": "calculateCubicStartingPoint(uint256,uint256,uint256,uint256)",
  "f70b23ef": "calculateCubicTerms(uint256[],uint256)",
  "a2b57f01": "calculateInvariant(uint256[],uint256)",
  "0c7e115f": "liquidityInvariantUpdate(uint256,uint256,uint256,bool)",
  "cb2e3f31": "runNewtonIteration(uint256,uint256,uint256,uint256,uint256,uint256)",
  "ffd088eb": "getLargestSafeQueryWindow()",
  "b10be739": "getLatest(uint8)",
  "50ee5690": "getPastAccumulators(tuple[])",
  "d5d1f990": "getTimeWeightedAverage(tuple[])",
  "dd62ed3e": "allowance(address,address)",
  "095ea7b3": "approve(address,uint256)",
  "70a08231": "balanceOf(address)",
  "313ce567": "decimals()",
  "a457c2d7": "decreaseAllowance(address,uint256)",
  "39509351": "increaseAllowance(address,uint256)",
  "40c10f19": "mint(address,uint256)",
  "06fdde03": "name()",
  "8da5cb5b": "owner()",
  "715018a6": "renounceOwnership()",
  "95d89b41": "symbol()",
  "18160ddd": "totalSupply()",
  "a9059cbb": "transfer(address,uint256)",
  "23b872dd": "transferFrom(address,address,uint256)",
  "f2fde38b": "transferOwnership(address)",
  "aaabadc5": "getAuthorizer()",
  "e42abf35": "getCollectedFeeAmounts(address[])",
  "d877845c": "getFlashLoanFeePercentage()",
  "55c67628": "getSwapFeePercentage()",
  "6b6b9f69": "setFlashLoanFeePercentage(uint256)",
  "38e9922e": "setSwapFeePercentage(uint256)",
  "fbfa77cf": "vault()",
  "6daefab6": "withdrawCollectedFees(address[],uint256[],address)",
  "ed24911d": "getDomainSeparator()",
  "90193b7c": "getNextNonce(address)",
  "21f8a721": "getAddress(bytes32)",
  "bd02d0f5": "getUint(bytes32)",
  "fd322c14": "listKeys()",
  "ca446dd9": "setAddress(bytes32,address)",
  "e2a4853a": "setUint(bytes32,uint256)",
  "abb9d0d5": "fromLowResLog(int256)",
  "57aad013": "toLowResLog(uint256)",
  "db9ddcd3": "calcInGivenOut(uint256[],uint256,bool,(int256,int256,int256,int256,int256),((int256,int256),(int256,int256),int256,int256,int256,int256,int256),(int256,int256))",
  "8e4745e4": "calcOutGivenIn(uint256[],uint256,bool,(int256,int256,int256,int256,int256),((int256,int256),(int256,int256),int256,int256,int256,int256,int256),(int256,int256))",
  "b8cd6f60": "calculateInvariant(uint256[],(int256,int256,int256,int256,int256),((int256,int256),(int256,int256),int256,int256,int256,int256,int256))",
  "ecb44af4": "calculateInvariantWithError(uint256[],(int256,int256,int256,int256,int256),((int256,int256),(int256,int256),int256,int256,int256,int256,int256))",
  "dc68c476": "calculatePrice(uint256[],(int256,int256,int256,int256,int256),((int256,int256),(int256,int256),int256,int256,int256,int256,int256),int256)",
  "1184b0fc": "validateDerivedParamsLimits((int256,int256,int256,int256,int256),((int256,int256),(int256,int256),int256,int256,int256,int256,int256))",
  "851c1bb3": "getActionId(bytes4)",
  "893d20e8": "getOwner()",
  "00c194db": "getCreationCode()",
  "174481fa": "getCreationCodeContracts()",
  "8d928af8": "getVault()",
  "6634b753": "isPoolFromFactory(address)",
  "9be2a884": "canPerform(bytes32,address,address)",
  "d5905100": "calcInGivenOut(uint256,uint256,uint256,uint256,uint256)",
  "0c78bb4e": "calcOutGivenIn(uint256,uint256,uint256,uint256,uint256)",
  "3867bdac": "calculateInvariant(uint256[],uint256,uint256)",
  "f7eb3e1d": "calculateQuadratic(uint256,uint256,uint256,uint256)",
  "175b46d7": "calculateQuadraticTerms(uint256[],uint256,uint256)",
  "1a3f00b7": "calculateVirtualParameter0(uint256,uint256)",
  "d12f4625": "calculateVirtualParameter1(uint256,uint256)",
  "677342ce": "sqrt(uint256)",
  "8002df18": "changePauseManager(address)",
  "8456cb59": "pause()",
  "abd13afe": "pauseManager()",
  "3f4ba83a": "unpause()",
  "3644e515": "DOMAIN_SEPARATOR()",
  "3c4dd5bb": "calculateCurrentValues(uint256,uint256,bool)",
  "6d785a87": "capManager()",
  "3aeae0d3": "capParams()",
  "3331bc36": "dirtyUninitializedOracleSamples(uint256,uint256)",
  "292c914a": "enableOracle()",
  "c0ff1a15": "getInvariant()",
  "9b02cdde": "getLastInvariant()",
  "4a6b0b15": "getMiscData()",
  "f89f27ed": "getNormalizedWeights()",
  "1c0de051": "getPausedState()",
  "38fff2d0": "getPoolId()",
  "679aefce": "getRate()",
  "60d1507c": "getSample(uint256)",
  "707dcd1e": "getSqrtParameters()",
  "b48b5b40": "getTotalSamples()",
  "8dd9f89d": "getVirtualParameters()",
  "44bbdb55": "gyroConfig()",
  "7ecebe00": "nonces(address)",
  "74f3b009": "onExitPool(bytes32,address,address,uint256[],uint256,uint256,bytes)",
  "d5c096c4": "onJoinPool(bytes32,address,address,uint256[],uint256,uint256,bytes)",
  "9d2c110c": "onSwap((uint8,address,address,uint256,bytes32,uint256,address,address,bytes),uint256,uint256)",
  "d505accf": "permit(address,address,uint256,uint256,uint8,bytes32,bytes32)",
  "6028bfd4": "queryExit(bytes32,address,address,uint256[],uint256,uint256,bytes)",
  "87ec6817": "queryJoin(bytes32,address,address,uint256[],uint256,uint256,bytes)",
  "0e608b30": "setCapManager(address)",
  "76e54a46": "setCapParams((bool,uint120,uint128))",
  "16c38b3c": "setPaused(bool)",
  "ad5c4648": "WETH()",
  "ea315d46": "batchSwap(uint8,tuple[],address[],(address,bool,address,bool),int256[],uint256)",
  "7d3aeb96": "deregisterTokens(bytes32,address[])",
  "8bdb3913": "exitPool(bytes32,address,address,(address[],uint256[],bytes,bool))",
  "5c38449e": "flashLoan(address,address[],uint256[],bytes)",
  "0f5a6efa": "getInternalBalance(address,address[])",
  "f6c00927": "getPool(bytes32)",
  "b05f8e48": "getPoolTokenInfo(bytes32,address)",
  "f94d4668": "getPoolTokens(bytes32)",
  "d2946c2b": "getProtocolFeesCollector()",
  "fec90d72": "hasApprovedRelayer(address,address)",
  "b95cac28": "joinPool(bytes32,address,address,(address[],uint256[],bytes,bool))",
  "03f4a834": "managePoolBalance(tuple[])",
  "1ec24dd9": "manageUserBalance(tuple[])",
  "3b533f5b": "queryBatchSwap(uint8,tuple[],address[],(address,bool,address,bool))",
  "09b2760f": "registerPool(uint8)",
  "66a9c7d2": "registerTokens(bytes32,address[],address[])",
  "058a628f": "setAuthorizer(address)",
  "fa6e671d": "setRelayerApproval(address,address,bool)",
  "52bbbe29": "swap((bytes32,uint8,address,address,uint256,bytes),(address,bool,address,bool),uint256,uint256)",
  "d1464686": "BUFFER_PERIOD_DURATION()",
  "45be0bd4": "PAUSE_WINDOW_DURATION()",
  "286f6cf0": "create((string,string,address[],uint256,uint256,address,address,(bool,uint120,uint128),address))",
  "2da47c40": "getPauseConfiguration()",
  "0bc7b4c4": "gyroConfigAddress()",
  "1dd746ea": "getScalingFactors()",
  "50dd6ed9": "setAssetManagerPoolConfig(address,bytes)",
  "f04f2707": "receiveFlashLoan(address[],uint256[],uint256[],bytes)",
  "ff2e03ea": "calcLogBPTPrice(uint256,uint256,uint256,uint256,int256)",
  "c519a075": "calcLogSpotPrice(uint256,uint256,uint256,uint256)",
  "5d14552a": "calcSpotPrice(uint256,uint256,uint256,uint256)",
  "b8acd8ad": "callExitPoolGyro(address,bytes32,address,address,uint256[],uint256,uint256,uint256)",
  "0b08cf89": "callGeneralPoolSwap(address,(uint8,address,address,uint256,bytes32,uint256,address,address,bytes),uint256[],uint256,uint256)",
  "fb177ff5": "callJoinPoolGyro((address,bytes32,address,address,uint256[],uint256,uint256,uint256[],uint256))",
  "8acd6b9d": "callMinimalGyroPoolSwap(address,(uint8,address,address,uint256,bytes32,uint256,address,address,bytes),uint256,uint256)",
  "f76102db": "callMinimalPoolSwap(address,(uint8,address,address,uint256,bytes32,uint256,address,address,bytes),uint256,uint256)",
  "1865221a": "updateBalances(bytes32,uint256[])",
  "34e7a19f": "joinPool(uint256)",
  "f851a440": "admin()",
  "8f283970": "changeAdmin(address)",
  "62a5af3b": "freeze()",
  "5c60da1b": "implementation()",
  "3659cfe6": "upgradeTo(address)",
  "4f1ef286": "upgradeToAndCall(address,bytes)",
  "35371819": "create(string,string,address[],(int256,int256,int256,int256,int256),((int256,int256),(int256,int256),int256,int256,int256,int256,int256),uint256,bool,address,address,(bool,uint120,uint128),address)",
  "d60ca603": "getRoot3Alpha()",
  "771602f7": "add(uint256,uint256)",
  "c8a4ac9c": "mul(uint256,uint256)",
  "aac31011": "sqrtNewton(uint256,uint256)",
  "f46292f4": "sqrtNewtonInitialGuess(uint256)",
  "b67d77c5": "sub(uint256,uint256)",
  "ad59d558": "truediv(uint256,uint256)",
  "ce482387": "_dSq()",
  "bcc43692": "_paramsAlpha()",
  "1469ed6c": "_paramsBeta()",
  "66e9ddf4": "_paramsC()",
  "591a137f": "_paramsLambda()",
  "c4fea7c9": "_paramsS()",
  "58ecbcc3": "_tauAlphaX()",
  "ddb387c9": "_tauAlphaY()",
  "7ef355cd": "_tauBetaX()",
  "1d86bb99": "_tauBetaY()",
  "2024cf41": "_u()",
  "c2c3bd6a": "_v()",
  "8143eb76": "_w()",
  "dc09f3aa": "_z()",
  "7be219a2": "getECLPParams()",
  "a217fddf": "DEFAULT_ADMIN_ROLE()",
  "248a9ca3": "getRoleAdmin(bytes32)",
  "9010d07c": "getRoleMember(bytes32,uint256)",
  "ca15c873": "getRoleMemberCount(bytes32)",
  "2f2ff15d": "grantRole(bytes32,address)",
  "fcd7627e": "grantRoles(bytes32[],address)",
  "a73cb2ab": "grantRolesToMany(bytes32[],address[])",
  "91d14854": "hasRole(bytes32,address)",
  "36568abe": "renounceRole(bytes32,address)",
  "d547741f": "revokeRole(bytes32,address)",
  "988360a3": "revokeRoles(bytes32[],address)",
  "18b2cde9": "revokeRolesFromMany(bytes32[],address[])",
  "f4abb15c": "create(string,string,address[],uint256[],uint256,bool,address,address,(bool,uint120,uint128),address)",
  "906c4175": "_calcAllTokensInGivenExactBptOut(uint256[],uint256,uint256)",
  "f5875470": "_calcProtocolFees(uint256,uint256,uint256,uint256,uint256)",
  "2d09954d": "_calcTokensOutGivenExactBptIn(uint256[],uint256,uint256)",
  "5e5f55f8": "calc2AtxAtyAChixAChiy(int256,int256,(int256,int256,int256,int256,int256),((int256,int256),(int256,int256),int256,int256,int256,int256,int256))",
  "a338c7ff": "calcAChiAChiInXp((int256,int256,int256,int256,int256),((int256,int256),(int256,int256),int256,int256,int256,int256,int256))",
  "11ebc74e": "calcAtAChi(int256,int256,(int256,int256,int256,int256,int256),((int256,int256),(int256,int256),int256,int256,int256,int256,int256))",
  "2453ffde": "calcInvariantSqrt(int256,int256,(int256,int256,int256,int256,int256),((int256,int256),(int256,int256),int256,int256,int256,int256,int256))",
  "44b62bf9": "calcMinAtxAChiySqPlusAtxSq(int256,int256,(int256,int256,int256,int256,int256),((int256,int256),(int256,int256),int256,int256,int256,int256,int256))",
  "98778a4e": "calcMinAtyAChixSqPlusAtySq(int256,int256,(int256,int256,int256,int256,int256),((int256,int256),(int256,int256),int256,int256,int256,int256,int256))",
  "aa71aa6b": "calcXGivenY(int256,(int256,int256,int256,int256,int256),((int256,int256),(int256,int256),int256,int256,int256,int256,int256),(int256,int256))",
  "118d6652": "calcXpXpDivLambdaLambda(int256,(int256,int256),int256,int256,int256,(int256,int256),int256)",
  "c6bab286": "calcYGivenX(int256,(int256,int256,int256,int256,int256),((int256,int256),(int256,int256),int256,int256,int256,int256,int256),(int256,int256))",
  "bb87e63a": "checkAssetBounds((int256,int256,int256,int256,int256),((int256,int256),(int256,int256),int256,int256,int256,int256,int256),(int256,int256),int256,uint8)",
  "84763176": "maxBalances0((int256,int256,int256,int256,int256),((int256,int256),(int256,int256),int256,int256,int256,int256,int256),(int256,int256))",
  "53992224": "maxBalances1((int256,int256,int256,int256,int256),((int256,int256),(int256,int256),int256,int256,int256,int256,int256),(int256,int256))",
  "de031937": "mulA((int256,int256,int256,int256,int256),(int256,int256))",
  "442373f6": "scalarProd((int256,int256),(int256,int256))",
  "5733b46d": "solveQuadraticSwap(int256,int256,int256,int256,(int256,int256),(int256,int256),(int256,int256),int256)",
  "dc446e7d": "virtualOffset0((int256,int256,int256,int256,int256),((int256,int256),(int256,int256),int256,int256,int256,int256,int256),(int256,int256))",
  "36a315c7": "virtualOffset1((int256,int256,int256,int256,int256),((int256,int256),(int256,int256),int256,int256,int256,int256,int256),(int256,int256))",
  "008821bd": "calcLogBPTPrice(uint256,uint256,uint256,int256)",
  "a7cba969": "calcLogInvariantDivSupply(uint256,int256)",
  "b47a34a1": "calcLogSpotPrice(uint256)",
  "01ec954a": "onSwap((uint8,address,address,uint256,bytes32,uint256,address,address,bytes),uint256[],uint256,uint256)",
  "2b13a509": "capitalOut(bytes32,uint256)",
  "dc99fc21": "getAUM(bytes32)",
  "76bad529": "getPoolBalances(bytes32)",
  "21df0da7": "getToken()",
  "ea748923": "maxInvestableBalance(bytes32)",
  "4c936d8a": "rebalance(bytes32,bool)",
  "18e736d4": "setConfig(bytes32,bytes)",
  "9c64ad30": "shouldRebalance(uint256,uint256)",
  "0b5ff6b9": "updateBalanceOfPool(bytes32)",
  "3bdeb560": "BAL_TREASURY_KEY()",
  "e3e457ac": "GYRO_TREASURY_KEY()",
  "5a1890b3": "PROTOCOL_FEE_GYRO_PORTION_KEY()",
  "b6b0774a": "PROTOCOL_SWAP_FEE_PERC_KEY()",
  "d0e30db0": "deposit()",
  "2e1a7d4d": "withdraw(uint256)",
  "9ba5f52e": "divDown(uint256,uint256)",
  "7a5a09bb": "divDownLarge(uint256,uint256)",
  "e2a6d234": "divDownLarge(uint256,uint256,uint256,uint256)",
  "0e8d3543": "divDownLargeU(uint256,uint256)",
  "d60e34ff": "divDownLargeU(uint256,uint256,uint256,uint256)",
  "f89151f5": "divDownU(uint256,uint256)",
  "cbe8623f": "divUp(uint256,uint256)",
  "f7441cac": "divUpU(uint256,uint256)",
  "0c9b9881": "mulDown(uint256,uint256)",
  "6b60beab": "mulDownLargeSmall(uint256,uint256)",
  "8e59a97d": "mulDownLargeSmallU(uint256,uint256)",
  "bfc0a96d": "mulDownU(uint256,uint256)",
  "f3e4f87c": "mulUp(uint256,uint256)",
  "0ac74894": "mulUpU(uint256,uint256)",
  "8542fd76": "_intLog2Halved(uint256)",
  "e8e3af1f": "findNearestSample(uint256,uint256,uint256)",
  "264959fb": "getPastAccumulator(uint8,uint256,uint256)",
  "a5f3c23b": "add(int256,int256)",
  "1907db72": "addMag(int256,int256)",
  "ddb29e92": "divDown(int256,int256)",
  "47ee9ec2": "divDownU(int256,int256)",
  "e2bec1fe": "divUp(int256,int256)",
  "71c3f2bb": "divUpU(int256,int256)",
  "90c27b70": "divXp(int256,int256)",
  "7abcad4c": "divXpU(int256,int256)",
  "bbe93d91": "mul(int256,int256)",
  "4b8d10e0": "mulDown(int256,int256)",
  "33368aae": "mulDownU(int256,int256)",
  "db05921e": "mulDownXpToNp(int256,int256)",
  "ff2121f4": "mulDownXpToNpU(int256,int256)",
  "1aabb2f7": "mulUp(int256,int256)",
  "1d5993c2": "mulUpU(int256,int256)",
  "ec1215ba": "mulUpXpToNp(int256,int256)",
  "9451f60d": "mulUpXpToNpU(int256,int256)",
  "5ecd3e24": "mulXp(int256,int256)",
  "14bf8d30": "mulXpU(int256,int256)",
  "adefc37b": "sub(int256,int256)",
  "a1b9391b": "truediv(int256,int256)"
}